README.md
setup.cfg
setup.py
Split_SD_For_Explaining.egg-info/PKG-INFO
Split_SD_For_Explaining.egg-info/SOURCES.txt
Split_SD_For_Explaining.egg-info/dependency_links.txt
Split_SD_For_Explaining.egg-info/top_level.txt
splitsd/__init__.py
splitsd/dataPreprocessing.py
splitsd/explanations.py
splitsd/missing_values_table.py
splitsd/neighborsGeneration.py
splitsd/patternsExtraction.py
splitsd/performances.py
splitsd/splitsd.py
splitsd/toCompare.py