Metadata-Version: 2.1
Name: Split-SD-For-Explaining
Version: 0.1
Summary: Split SD for explanations
Home-page: https://github.com/RemilYoucef/Split-SD-For-Explaining
Author: Youcef REMIL
Author-email: fy_remil@esi.dz
License: UNKNOWN
Platform: UNKNOWN
Classifier: Programming Language :: Python :: 3
Classifier: License :: OSI Approved :: MIT License
Classifier: Operating System :: OS Independent
Requires-Python: >=3.6
